README.md
setup.py
SAW/__init__.py
SAW/client.py
SAW/company.py
SAW/http_client.py
SAW.egg-info/PKG-INFO
SAW.egg-info/SOURCES.txt
SAW.egg-info/dependency_links.txt
SAW.egg-info/entry_points.txt
SAW.egg-info/requires.txt
SAW.egg-info/top_level.txt
scripts/__init__.py
scripts/saw.py