Metadata-Version: 2.1
Name: SAW
Version: 0.1.1
Summary: SAW, a Python SimFin API Wrapper
Home-page: UNKNOWN
Author: Vilhelm Melkstam
Author-email: vilhelm.melkstam@gmail.com
License: MIT License
Platform: UNKNOWN
Classifier: License :: OSI Approved :: MIT License
Classifier: Programming Language :: Python
Classifier: Programming Language :: Python :: 3
Classifier: Programming Language :: Python :: 3.7
Classifier: Topic :: Documentation :: Sphinx
Classifier: Topic :: Office/Business :: Financial
Classifier: Topic :: Office/Business :: Financial :: Investment
Classifier: Topic :: Utilities
